import_order/__init__.py
import_order/cli.py
import_order/filter.py
import_order/inspect.py
import_order/listing.py
import_order/sort.py
import_order/version.py
import_order-0.0.11.dist-info/DESCRIPTION.rst
import_order-0.0.11.dist-info/METADATA
import_order-0.0.11.dist-info/RECORD
import_order-0.0.11.dist-info/WHEEL
import_order-0.0.11.dist-info/entry_points.txt
import_order-0.0.11.dist-info/metadata.json
import_order-0.0.11.dist-info/top_level.txt
tests/__init__.py
tests/filter_test.py
tests/inspect_test.py
tests/mock.py
tests/sort_test.py
