Metadata-Version: 2.0
Name: import-order
Version: 0.0.11
Summary: Check python import order.
Home-page: https://github.com/spoqa/import-order
Author: Spoqa
Author-email: dev@spoqa.com
License: UNKNOWN
Platform: UNKNOWN
Classifier: Development Status :: 4 - Beta
Classifier: Environment :: Console
Classifier: Intended Audience :: Developers
Classifier: Operating System :: Unix
Classifier: Programming Language :: Python :: 2
Classifier: Programming Language :: Python :: 2.7
Classifier: Programming Language :: Python :: 3
Classifier: Programming Language :: Python :: 3.3
Classifier: Programming Language :: Python :: 3.4
Classifier: Programming Language :: Python :: 3.5
Classifier: Topic :: Software Development :: Libraries :: Python Modules
Classifier: Topic :: Software Development :: Quality Assurance
Requires-Dist: Pygments (>=2.0.2,<2.1.0)
Provides-Extra: tests
Requires-Dist: pytest (>=2.7.0); extra == 'tests'
Requires-Dist: tox; extra == 'tests'
